invenio_logging/__init__.py
invenio_logging/config.py
invenio_logging/console.py
invenio_logging/ext.py
invenio_logging/fs.py
invenio_logging/sentry.py
invenio_logging/utils.py
invenio_logging-4.1.1.dist-info/licenses/AUTHORS.rst
invenio_logging-4.1.1.dist-info/licenses/LICENSE
invenio_logging-4.1.1.dist-info/METADATA
invenio_logging-4.1.1.dist-info/WHEEL
invenio_logging-4.1.1.dist-info/entry_points.txt
invenio_logging-4.1.1.dist-info/top_level.txt
invenio_logging-4.1.1.dist-info/RECORD
