Metadata-Version: 2.4
Name: invenio-logging
Version: 4.1.1
Summary: "Module providing logging capabilities."
Home-page: https://github.com/inveniosoftware/invenio-logging
Author: CERN
Author-email: info@inveniosoftware.org
License: MIT
Keywords: invenio logging
Platform: any
Classifier: Development Status :: 5 - Production/Stable
Requires-Python: >=3.8
License-File: LICENSE
License-File: AUTHORS.rst
Requires-Dist: invenio-celery<3.0.0,>=2.0.0
Requires-Dist: invenio-db<3.0.0,>=2.0.0
Provides-Extra: tests
Requires-Dist: pytest-black-ng>=0.4.0; extra == "tests"
Requires-Dist: flask-login>=0.6.1; extra == "tests"
Requires-Dist: httpretty>=0.8.14; extra == "tests"
Requires-Dist: mock>=1.3.0; extra == "tests"
Requires-Dist: pytest-invenio<4.0.0,>=3.0.0; extra == "tests"
Requires-Dist: iniconfig>=1.1.1; extra == "tests"
Requires-Dist: sphinx>=4.5; extra == "tests"
Requires-Dist: sentry-sdk[flask]<2.0.0,>=1.0.0; extra == "tests"
Provides-Extra: sentry
Requires-Dist: sentry-sdk[flask]<2.0.0,>=1.0.0; extra == "sentry"
Dynamic: license-file
